teklia_yolo_worker-1.2.6.dist-info/licenses/LICENSE
tests/__init__.py
tests/conftest.py
tests/test_classifier.py
tests/test_inference.py
tests/test_segmenter.py
tests/test_training.py
tests/offline/__init__.py
tests/offline/conftest.py
tests/offline/test_classifier.py
tests/offline/test_publish.py
worker_yolo/__init__.py
worker_yolo/classifier.py
worker_yolo/segmenter.py
worker_yolo/utils.py
worker_yolo/worker.py
worker_yolo/offline/__init__.py
worker_yolo/offline/classifier.py
worker_yolo/offline/preprocess.py
worker_yolo/offline/publish.py
worker_yolo/train/__init__.py
worker_yolo/train/base.py
worker_yolo/train/classification.py
worker_yolo/train/detection.py
teklia_yolo_worker-1.2.6.dist-info/METADATA
teklia_yolo_worker-1.2.6.dist-info/WHEEL
teklia_yolo_worker-1.2.6.dist-info/entry_points.txt
teklia_yolo_worker-1.2.6.dist-info/top_level.txt
teklia_yolo_worker-1.2.6.dist-info/RECORD
