Metadata-Version: 2.4
Name: teklia-yolo-worker
Version: 1.2.6
Summary: Ultralytics YOLO
Author-email: Teklia <contact@teklia.com>
Maintainer-email: Teklia <contact@teklia.com>
Keywords: python
Classifier: Programming Language :: Python :: 3 :: Only
Classifier: Programming Language :: Python :: 3.10
Classifier: Programming Language :: Python :: 3.11
Classifier: Programming Language :: Python :: 3.12
Requires-Python: >=3.10
License-File: LICENSE
Requires-Dist: arkindex-base-worker==0.5.1.post1
Requires-Dist: openai-clip==1.0.1
Requires-Dist: teklia-yolo==0.2.4
Requires-Dist: ultralytics==8.3.197
Dynamic: license-file
